Hershey01/Test001.py
Hershey01/TurtleShow.py
Hershey01/__init__.py
Hershey01/GsDict/Library.py
Hershey01/GsDict/astrology.gsdict
Hershey01/GsDict/cursive.gsdict
Hershey01/GsDict/cyrilc_1.gsdict
Hershey01/GsDict/cyrillic.gsdict
Hershey01/GsDict/futural.gsdict
Hershey01/GsDict/futuram.gsdict
Hershey01/GsDict/gothgbt.gsdict
Hershey01/GsDict/gothgrt.gsdict
Hershey01/GsDict/gothiceng.gsdict
Hershey01/GsDict/gothicger.gsdict
Hershey01/GsDict/gothicita.gsdict
Hershey01/GsDict/gothitt.gsdict
Hershey01/GsDict/greek.gsdict
Hershey01/GsDict/greekc.gsdict
Hershey01/GsDict/greeks.gsdict
Hershey01/GsDict/japanese.gsdict
Hershey01/GsDict/markers.gsdict
Hershey01/GsDict/mathlow.gsdict
Hershey01/GsDict/mathupp.gsdict
Hershey01/GsDict/meteorology.gsdict
Hershey01/GsDict/music.gsdict
Hershey01/GsDict/rowmand.gsdict
Hershey01/GsDict/rowmans.gsdict
Hershey01/GsDict/rowmant.gsdict
Hershey01/GsDict/scriptc.gsdict
Hershey01/GsDict/scripts.gsdict
Hershey01/GsDict/symbolic.gsdict
Hershey01/GsDict/timesg.gsdict
Hershey01/GsDict/timesi.gsdict
Hershey01/GsDict/timesib.gsdict
Hershey01/GsDict/timesr.gsdict
Hershey01/GsDict/timesrb.gsdict
Hershey01/GsText/Reader.py
Hershey01/GsText/Test.py
Hershey01/VectorFont/Font.py
Hershey01/VectorFont/FontData.py
PyHershey_9000-1.0.0.data/data/Hershey01/GsDict/astrology.gsdict
PyHershey_9000-1.0.0.data/data/Hershey01/GsDict/cursive.gsdict
PyHershey_9000-1.0.0.data/data/Hershey01/GsDict/cyrilc_1.gsdict
PyHershey_9000-1.0.0.data/data/Hershey01/GsDict/cyrillic.gsdict
PyHershey_9000-1.0.0.data/data/Hershey01/GsDict/futural.gsdict
PyHershey_9000-1.0.0.data/data/Hershey01/GsDict/futuram.gsdict
PyHershey_9000-1.0.0.data/data/Hershey01/GsDict/gothgbt.gsdict
PyHershey_9000-1.0.0.data/data/Hershey01/GsDict/gothgrt.gsdict
PyHershey_9000-1.0.0.data/data/Hershey01/GsDict/gothiceng.gsdict
PyHershey_9000-1.0.0.data/data/Hershey01/GsDict/gothicger.gsdict
PyHershey_9000-1.0.0.data/data/Hershey01/GsDict/gothicita.gsdict
PyHershey_9000-1.0.0.dist-info/METADATA
PyHershey_9000-1.0.0.dist-info/WHEEL
PyHershey_9000-1.0.0.dist-info/top_level.txt
PyHershey_9000-1.0.0.dist-info/RECORD
