Metadata-Version: 2.1
Name: PyHershey-9000
Version: 1.0.0
Summary: Hershey's Vector Fonts
Home-page: http://soft9000.com
Download-URL: https://github.com/soft9000/PyHershey
Author: Randall Nagy
Author-email: Randall Nagy <r.a.nagy@gmail.com>
Project-URL: Homepage, https://github.com/soft9000/PyHershey
Project-URL: Bug Tracker, https://github.com/soft9000/PyHershey/issues
Platform: Turtle Graphics Required
Classifier: Programming Language :: Python :: 3
Classifier: License :: OSI Approved :: MIT License
Classifier: Operating System :: OS Independent
Requires-Python: >=3.6
